{
	"image": "INGAME_MENU_LEADERBOARDS.png",
	"spriteCount": 26,
	"sprite_0": { "id": "BG_PROFILEPIC", "x": 627, "y": 161, "width": 60, "height": 60, "pivotx": 30, "pivoty": 30 },
	"sprite_1": { "id": "BUTTON_LB_SMALL_INACTIVE", "x": 627, "y": 1, "width": 78, "height": 78, "pivotx": 39, "pivoty": 39 },
	"sprite_2": { "id": "BUTTON_LB_SMALL_ACTIVE", "x": 627, "y": 81, "width": 78, "height": 78, "pivotx": 39, "pivoty": 39 },
	"sprite_3": { "id": "TEXT_LB_NEXT", "x": 686, "y": 285, "width": 56, "height": 51, "pivotx": 28, "pivoty": 25 },
	"sprite_4": { "id": "TEXT_LB_TOP", "x": 627, "y": 285, "width": 57, "height": 58, "pivotx": 28, "pivoty": 29 },
	"sprite_5": { "id": "TEXT_LB_YOU", "x": 571, "y": 562, "width": 56, "height": 51, "pivotx": 28, "pivoty": 25 },
	"sprite_6": { "id": "TEXT_LB_PREV", "x": 200, "y": 703, "width": 56, "height": 51, "pivotx": 28, "pivoty": 25 },
	"sprite_7": { "id": "BUTTON_LB_INVITE", "x": 1, "y": 703, "width": 197, "height": 62, "pivotx": 98, "pivoty": 31 },
	"sprite_8": { "id": "ICON_LB_STAR", "x": 707, "y": 1, "width": 22, "height": 21, "pivotx": 11, "pivoty": 11 },
	"sprite_9": { "id": "ICON_LB_NOSTAR", "x": 707, "y": 24, "width": 22, "height": 21, "pivotx": 11, "pivoty": 11 },
	"sprite_10": { "id": "ICON_NO_PROFILEPIC", "x": 689, "y": 161, "width": 50, "height": 50, "pivotx": 25, "pivoty": 25 },
	"sprite_11": { "id": "TITLE_LEADERBOARD", "x": 1, "y": 636, "width": 302, "height": 65, "pivotx": 0, "pivoty": 0 },
	"sprite_12": { "id": "POPUP_LEADERBOARD_BG", "x": 1, "y": 1, "width": 624, "height": 371, "pivotx": 0, "pivoty": 0 },
	"sprite_13": { "id": "BG_PROFILEPIC_RAGGED", "x": 627, "y": 223, "width": 60, "height": 60, "pivotx": 30, "pivoty": 30 },
	"sprite_14": { "id": "BG_POPUP_LEADERBOARDS_1", "x": 305, "y": 636, "width": 414, "height": 62, "pivotx": 0, "pivoty": 0 },
	"sprite_15": { "id": "BG_POPUP_LEADERBOARDS_2", "x": 305, "y": 700, "width": 178, "height": 62, "pivotx": 0, "pivoty": 0 },
	"sprite_16": { "id": "ICON_ARROW", "x": 689, "y": 223, "width": 49, "height": 39, "pivotx": 24, "pivoty": 19 },
	"sprite_17": { "id": "EMPTY_SLOT", "x": 485, "y": 700, "width": 231, "height": 56, "pivotx": 0, "pivoty": 0 },
	"sprite_18": { "id": "TEXT_LB_BOTTOM", "x": 571, "y": 502, "width": 57, "height": 58, "pivotx": 28, "pivoty": 29 },
	"sprite_19": { "id": "BUTTON_LB_POST", "x": 571, "y": 374, "width": 121, "height": 62, "pivotx": 60, "pivoty": 31 },
	"sprite_20": { "id": "BUTTON_LB_BRAG", "x": 571, "y": 438, "width": 121, "height": 62, "pivotx": 60, "pivoty": 31 },
	"sprite_21": { "id": "STRIPED_BG", "x": 1, "y": 374, "width": 568, "height": 260, "pivotx": 0, "pivoty": 1 },
	"sprite_22": { "id": "TOOLTIP_BRAG", "x": 630, "y": 502, "width": 108, "height": 51, "pivotx": 54, "pivoty": 25 },
	"sprite_23": { "id": "TOOLTIP_POST", "x": 630, "y": 555, "width": 108, "height": 51, "pivotx": 54, "pivoty": 25 },
	"sprite_24": { "id": "TOOLTIP_LEADERBOARD", "x": 485, "y": 758, "width": 146, "height": 51, "pivotx": 73, "pivoty": 25 },
	"sprite_25": { "id": "TOOLTIP_INVITE", "x": 305, "y": 764, "width": 156, "height": 51, "pivotx": 78, "pivoty": 25 }
}
